PyPubSub-3.4.2.dist-info/DESCRIPTION.rst
PyPubSub-3.4.2.dist-info/METADATA
PyPubSub-3.4.2.dist-info/RECORD
PyPubSub-3.4.2.dist-info/WHEEL
PyPubSub-3.4.2.dist-info/metadata.json
PyPubSub-3.4.2.dist-info/top_level.txt
pubsub/LICENSE_BSD_Simple.txt
pubsub/RELEASE_NOTES.txt
pubsub/__init__.py
pubsub/pub.py
pubsub/core/__init__.py
pubsub/core/callables.py
pubsub/core/listener.py
pubsub/core/notificationmgr.py
pubsub/core/publisher.py
pubsub/core/topicargspec.py
pubsub/core/topicdefnprovider.py
pubsub/core/topicexc.py
pubsub/core/topicmgr.py
pubsub/core/topicobj.py
pubsub/core/topictreetraverser.py
pubsub/core/topicutils.py
pubsub/core/weakmethod.py
pubsub/utils/__init__.py
pubsub/utils/exchandling.py
pubsub/utils/misc.py
pubsub/utils/notification.py
pubsub/utils/topictreeprinter.py
pubsub/utils/xmltopicdefnprovider.py
