Metadata-Version: 2.0
Name: PyPubSub
Version: 3.4.2
Summary: Python Publish-Subscribe Package
Home-page: https://github.com/schollii/pypubsub
Author: Oliver Schoenborn
Author-email: oliver.schoenborn@gmail.com
License: BSD
Download-URL: https://github.com/schollii/pypubsub/releases
Keywords: publish subscribe observer pattern signal signals event events message messages messaging dispatch dispatching
Platform: UNKNOWN
Classifier: Development Status :: 5 - Production/Stable
Classifier: Intended Audience :: Developers
Classifier: License :: OSI Approved :: Python Software Foundation License
Classifier: Natural Language :: English
Classifier: Programming Language :: Python :: 2.7
Classifier: Topic :: Software Development :: Libraries :: Application Frameworks
Classifier: Topic :: Software Development :: Libraries :: Python Modules
Requires-Python: ==2.7.*
Requires-Dist: enum34
Requires-Dist: pathlib
